mapping/__init__.py
mapping/operations.py
py_to_bt_mapping-1.0.0.dist-info/METADATA
py_to_bt_mapping-1.0.0.dist-info/WHEEL
py_to_bt_mapping-1.0.0.dist-info/top_level.txt
py_to_bt_mapping-1.0.0.dist-info/RECORD
