Metadata-Version: 2.1
Name: py_to_bt_mapping
Version: 1.0.0
Summary: BT-Basic to Python Mapping
Home-page: https://bitbucket.it.keysight.com/projects/I3070SM/repos/i3070_2025/browse/BT_Basic_Mapping/operations.py?at=refs%2Fheads%2Ffeature%2FBT-Basic-to-Python-Mapping
Keywords: maps BT-Basic functions
Classifier: Intended Audience :: Developers
Classifier: Topic :: Software Development :: Libraries :: Python Modules
Classifier: Programming Language :: Python :: 3
Requires-Dist: pywin32>=306
Requires-Dist: pyserial>=3
